{
  "id": "1RFZGUrxII0",
  "url": "https://youtu.be/1RFZGUrxII0",
  "title": "Solve Tech Chicken Egg Problem",
  "description": null,
  "publish_date": "2023-06-03T00:00:00",
  "length": 15,
  "views": 1523,
  "channel": "Programming with John",
  "transcript": [
    {
      "text": "to get a job you need experience to get",
      "start": 0.33,
      "duration": 4.44
    },
    {
      "text": "experience you need a job how do you",
      "start": 3.03,
      "duration": 3.72
    },
    {
      "text": "break out of the cycle in programming",
      "start": 4.77,
      "duration": 4.02
    },
    {
      "text": "the answer is straightforward you use a",
      "start": 6.75,
      "duration": 4.8
    },
    {
      "text": "portfolio of work github.com account is",
      "start": 8.79,
      "duration": 4.86
    },
    {
      "text": "free it's a must-have for developers to",
      "start": 11.55,
      "duration": 4.82
    },
    {
      "text": "prove your skill",
      "start": 13.65,
      "duration": 2.72
    }
  ]
}
