{
  "id": "BtB2Pl0Hjho",
  "url": "https://youtu.be/BtB2Pl0Hjho",
  "title": "Never Too Late",
  "description": null,
  "publish_date": "2023-06-03T00:00:00",
  "length": 15,
  "views": 2,
  "channel": "Programming with John",
  "transcript": [
    {
      "text": "so if you get a job at Walmart Target or",
      "start": 1.899,
      "duration": 4.121
    },
    {
      "text": "certain other companies even part-time",
      "start": 4.759,
      "duration": 2.52
    },
    {
      "text": "they'll send you to college for free",
      "start": 6.02,
      "duration": 3.24
    },
    {
      "text": "also I can teach you how to code or you",
      "start": 7.279,
      "duration": 3.36
    },
    {
      "text": "can teach yourself you just need to",
      "start": 9.26,
      "duration": 2.82
    },
    {
      "text": "Google it and stick with it for a while",
      "start": 10.639,
      "duration": 3.841
    },
    {
      "text": "or you could go to a boot camp you got",
      "start": 12.08,
      "duration": 4.88
    },
    {
      "text": "options girl",
      "start": 14.48,
      "duration": 2.48
    }
  ]
}
