{
  "id": "s0h9c8rLUig",
  "url": "https://youtu.be/s0h9c8rLUig",
  "title": "#learntocode #devcrew #programming #techtok #devtok #cstok #howto #learnontiktok #coding #softwareen",
  "description": null,
  "publish_date": "2023-07-20T00:00:00",
  "length": 15,
  "views": 2673,
  "channel": "Programming with John",
  "transcript": [
    {
      "text": "hey thanks for the comment I disagree I",
      "start": 0.08,
      "duration": 3.299
    },
    {
      "text": "think it's easier to get a job if you",
      "start": 2.12,
      "duration": 2.639
    },
    {
      "text": "know react would love to see your data",
      "start": 3.379,
      "duration": 4.141
    },
    {
      "text": "here's mine 90 000 jobs for c-sharp",
      "start": 4.759,
      "duration": 5.46
    },
    {
      "text": "available on indeed.com today over 140k",
      "start": 7.52,
      "duration": 4.38
    },
    {
      "text": "for reactor JavaScript you'll also be",
      "start": 10.219,
      "duration": 3.181
    },
    {
      "text": "qualified for angular roles and",
      "start": 11.9,
      "duration": 2.76
    },
    {
      "text": "thousands of others that aren't counted",
      "start": 13.4,
      "duration": 3.319
    },
    {
      "text": "here",
      "start": 14.66,
      "duration": 2.059
    }
  ]
}
