{
  "id": "0kwgv0-Knu4",
  "url": "https://youtu.be/0kwgv0-Knu4",
  "title": "#ai #progamming #ml #machinelearning #greenscreensticker",
  "description": null,
  "publish_date": "2023-04-08T00:00:00",
  "length": 15,
  "views": 35,
  "channel": "Programming with John",
  "transcript": [
    {
      "text": "part two building an AI tool for the",
      "start": 0.24,
      "duration": 3.719
    },
    {
      "text": "Super Bass hackathon the initial stream",
      "start": 2.28,
      "duration": 3.18
    },
    {
      "text": "is on YouTube I'll be doing another one",
      "start": 3.959,
      "duration": 3.241
    },
    {
      "text": "later today and here's the repository",
      "start": 5.46,
      "duration": 3.3
    },
    {
      "text": "you can go to a pull request right now",
      "start": 7.2,
      "duration": 3.42
    },
    {
      "text": "it's called rect this tool listens to",
      "start": 8.76,
      "duration": 3.6
    },
    {
      "text": "tick tocks and it makes four outputs",
      "start": 10.62,
      "duration": 3.54
    },
    {
      "text": "check the readme for more and follow for",
      "start": 12.36,
      "duration": 4.1
    },
    {
      "text": "part three",
      "start": 14.16,
      "duration": 2.3
    }
  ]
}
