{
  "id": "rmgW3Ceh5t4",
  "url": "https://youtu.be/rmgW3Ceh5t4",
  "title": "CS new grad advice",
  "description": null,
  "publish_date": "2024-01-16T00:00:00",
  "length": 15,
  "views": 44,
  "channel": "Programming with John",
  "transcript": [
    {
      "text": "so I'm a self-taught developer I don't",
      "start": 0.24,
      "duration": 3.88
    },
    {
      "text": "have a CS degree so my expertise with",
      "start": 1.88,
      "duration": 4.12
    },
    {
      "text": "new grat is kind of limited but I found",
      "start": 4.12,
      "duration": 4.12
    },
    {
      "text": "this comment really insightful I don't",
      "start": 6.0,
      "duration": 3.719
    },
    {
      "text": "know if this is trending up trending",
      "start": 8.24,
      "duration": 3.6
    },
    {
      "text": "down trending sideways some companies do",
      "start": 9.719,
      "duration": 4.96
    },
    {
      "text": "it some don't Reddit useful link for",
      "start": 11.84,
      "duration": 5.28
    },
    {
      "text": "once",
      "start": 14.679,
      "duration": 2.441
    }
  ]
}
